cidrfield/__init__.py
cidrfield/lookups.py
cidrfield/models.py
cidrfield/schemas.py
cidrfield/tests.py
django_cidrfield-0.2.0.dist-info/LICENSE
django_cidrfield-0.2.0.dist-info/METADATA
django_cidrfield-0.2.0.dist-info/WHEEL
django_cidrfield-0.2.0.dist-info/top_level.txt
django_cidrfield-0.2.0.dist-info/RECORD
